wolf_new/__init__.py
wolf_new/config.py
wolf_new/info.py
wolf_new/main.py
wolf_new/utils.py
wolf_new-2.0.1.dist-info/METADATA
wolf_new-2.0.1.dist-info/WHEEL
wolf_new-2.0.1.dist-info/top_level.txt
wolf_new-2.0.1.dist-info/RECORD
