Metadata-Version: 2.1
Name: wolf-new
Version: 2.0.1
Summary: 基于nonebot2的狼人杀插件
Home-page: https://github.com/AbCooly/nonebot_plugin_wolf_kill
Author: AbCooly
Author-email: 298587827@qq.com
Classifier: Programming Language :: Python :: 3.8
Classifier: License :: OSI Approved :: MIT License
Classifier: Operating System :: OS Independent
Requires-Python: >=3.7
Requires-Dist: nonebot2
Requires-Dist: nonebot-adapter-onebot
